engineering_box_sdk/__init__.py
engineering_box_sdk/main.py
azhar_sdk-0.1.2.dist-info/METADATA
azhar_sdk-0.1.2.dist-info/WHEEL
azhar_sdk-0.1.2.dist-info/entry_points.txt
azhar_sdk-0.1.2.dist-info/top_level.txt
azhar_sdk-0.1.2.dist-info/RECORD
